point_picker_3d/main.py
point_picker_3d/ui.py
point_picker_3d-1.0.1.dist-info/LICENSE
point_picker_3d-1.0.1.dist-info/METADATA
point_picker_3d-1.0.1.dist-info/WHEEL
point_picker_3d-1.0.1.dist-info/top_level.txt
point_picker_3d-1.0.1.dist-info/RECORD
