Metadata-Version: 2.1
Name: point-picker-3d
Version: 1.0.1
Summary: A simple interface to pick points on a geometry file (e.g. stl, ply, obj, etc.) and to export the coordinates to a csv file.
Author-email: Cristiano Pizzamiglio <cristianopizzamiglio@gmail.com>
License: MIT License
Project-URL: Homepage, https://github.com/CristianoPizzamiglio/point-picker-3d
Keywords: point,picker,3d
Classifier: Programming Language :: Python :: 3
Classifier: License :: OSI Approved :: BSD License
Classifier: Operating System :: OS Independent
Requires-Python: >=3.7
License-File: LICENSE
Requires-Dist: pyvistaqt (>=0.9)
Requires-Dist: PyQt5 (>=5.15)
